time_str/__init__.py
time_str/dt.py
time_str/interval.py
time_str/py.typed
time_str-1.0.0.dist-info/LICENSE
time_str-1.0.0.dist-info/METADATA
time_str-1.0.0.dist-info/WHEEL
time_str-1.0.0.dist-info/top_level.txt
time_str-1.0.0.dist-info/RECORD
