Metadata-Version: 2.1
Name: time-str
Version: 1.0.0
Summary: A package to convert user input into datetime.timedelta objects
Home-page: https://github.com/BobDotCom/time_str
Author: BobDotCom
Author-email: bobdotcomgt@gmail.com
License: MIT
Project-URL: Documentation, https://time-str.readthedocs.io/en/latest/index.html
Project-URL: Source, https://github.com/BobDotCom/time_str
Project-URL: Tracker, https://github.com/BobDotCom/time_str/issues
Classifier: Development Status :: 5 - Production/Stable
Classifier: License :: OSI Approved :: MIT License
Classifier: Intended Audience :: Developers
Classifier: Natural Language :: English
Classifier: Operating System :: OS Independent
Classifier: Programming Language :: Python :: 3.7
Classifier: Programming Language :: Python :: 3.8
Classifier: Programming Language :: Python :: 3.9
Classifier: Programming Language :: Python :: 3.10
Classifier: Topic :: Software Development :: Libraries
Classifier: Topic :: Software Development :: Libraries :: Python Modules
Classifier: Topic :: Utilities
Classifier: Typing :: Typed
Requires-Python: >=3.7
License-File: LICENSE
Requires-Dist: typing-extensions (>=3.10.0) ; python_version < "3.8"
Provides-Extra: all
Requires-Dist: mypy (==0.971) ; extra == 'all'
Requires-Dist: sphinx-rtd-theme (==1.0.0) ; extra == 'all'
Requires-Dist: pylint (==2.15.2) ; extra == 'all'
Requires-Dist: pre-commit (==2.20.0) ; extra == 'all'
Requires-Dist: pytest (==7.1.3) ; extra == 'all'
Requires-Dist: coverage (==6.4.4) ; extra == 'all'
Requires-Dist: typing-extensions (>=3.10.0) ; (python_version < "3.8") and extra == 'all'
Provides-Extra: dev
Requires-Dist: pytest (==7.1.3) ; extra == 'dev'
Requires-Dist: pylint (==2.15.2) ; extra == 'dev'
Requires-Dist: mypy (==0.971) ; extra == 'dev'
Requires-Dist: coverage (==6.4.4) ; extra == 'dev'
Requires-Dist: pre-commit (==2.20.0) ; extra == 'dev'
Requires-Dist: typing-extensions (>=3.10.0) ; (python_version < "3.8") and extra == 'dev'
Provides-Extra: docs
Requires-Dist: sphinx-rtd-theme (==1.0.0) ; extra == 'docs'
